autochain/__init__.py
autochain/agent/__init__.py
autochain/agent/base_agent.py
autochain/agent/conversational_agent/__init__.py
autochain/agent/conversational_agent/conversational_agent.py
autochain/agent/conversational_agent/output_parser.py
autochain/agent/conversational_agent/prompt.py
autochain/agent/conversational_agent/readme.md
autochain/agent/message.py
autochain/agent/openai_functions_agent/__init__.py
autochain/agent/openai_functions_agent/openai_functions_agent.py
autochain/agent/openai_functions_agent/output_parser.py
autochain/agent/openai_functions_agent/readme.md
autochain/agent/prompt_formatter.py
autochain/agent/structs.py
autochain/chain/__init__.py
autochain/chain/base_chain.py
autochain/chain/chain.py
autochain/chain/constants.py
autochain/chain/langchain_wrapper_chain.py
autochain/errors.py
autochain/examples/__init__.py
autochain/examples/get_weather_with_conversational_agent.py
autochain/examples/get_weather_with_openai_function_agent.py
autochain/examples/readme.md
autochain/examples/upsale_goal_conversational_agent.py
autochain/examples/write_poem_with_conversational_agent.py
autochain/memory/__init__.py
autochain/memory/base.py
autochain/memory/buffer_memory.py
autochain/memory/constants.py
autochain/memory/long_term_memory.py
autochain/memory/redis_memory.py
autochain/models/__init__.py
autochain/models/ada_embedding.py
autochain/models/base.py
autochain/models/chat_openai.py
autochain/models/huggingface_text_generation_model.py
autochain/models/readme.md
autochain/py.typed
autochain/tools/__init__.py
autochain/tools/base.py
autochain/tools/google_search/__init__.py
autochain/tools/google_search/tool.py
autochain/tools/google_search/util.py
autochain/tools/internal_search/__init__.py
autochain/tools/internal_search/base_search_tool.py
autochain/tools/internal_search/chromadb_tool.py
autochain/tools/internal_search/pinecone_tool.py
autochain/tools/simple_handoff/__init__.py
autochain/tools/simple_handoff/tool.py
autochain/utils.py
autochain-0.0.5.dist-info/LICENSE.txt
autochain-0.0.5.dist-info/METADATA
autochain-0.0.5.dist-info/WHEEL
autochain-0.0.5.dist-info/RECORD
