Metadata-Version: 2.1
Name: autochain
Version: 0.0.5
Summary: AutoChain: Build lightweight, extensible, and testable LLM Agents
Author: Yi Lu
Author-email: yi.lu@forethought.ai
Requires-Python: >=3.8.1,<4.0.0
Classifier: Development Status :: 4 - Beta
Classifier: Framework :: Pydantic
Classifier: Framework :: Pydantic :: 1
Classifier: Intended Audience :: Customer Service
Classifier: Intended Audience :: Developers
Classifier: Intended Audience :: Information Technology
Classifier: Intended Audience :: Science/Research
Classifier: Intended Audience :: System Administrators
Classifier: Operating System :: OS Independent
Classifier: Programming Language :: Python
Classifier: Programming Language :: Python :: 3
Classifier: Programming Language :: Python :: 3.9
Classifier: Programming Language :: Python :: 3.10
Classifier: Programming Language :: Python :: 3.11
Classifier: Programming Language :: Python :: 3
Classifier: Programming Language :: Python :: 3 :: Only
Classifier: Programming Language :: Python :: 3.10
Classifier: Programming Language :: Python :: 3.11
Classifier: Programming Language :: Python :: 3.12
Classifier: Programming Language :: Python :: 3.8
Classifier: Programming Language :: Python :: 3.9
Classifier: Topic :: Scientific/Engineering
Classifier: Topic :: Scientific/Engineering :: Artificial Intelligence
Classifier: Topic :: Software Development
Classifier: Topic :: Software Development :: Libraries
Classifier: Topic :: Software Development :: Libraries :: Application Frameworks
Classifier: Topic :: Software Development :: Libraries :: Python Modules
Classifier: Typing :: Typed
Provides-Extra: google
Provides-Extra: pinecone
Requires-Dist: chromadb (>=0.3.26)
Requires-Dist: colorama (>=0.4.6)
Requires-Dist: google-api-python-client (>=2.89.0) ; extra == "google"
Requires-Dist: mkdocs-git-authors-plugin (>=0.7.2,<0.8.0)
Requires-Dist: openai (>=0.27.8)
Requires-Dist: pandas (>=2.0.2)
Requires-Dist: pinecone-client (>=2.2.2,<3.0.0) ; extra == "pinecone"
Requires-Dist: pydantic (>=1.10.9,<2.0.0)
Requires-Dist: pytest (>=7.3.2,<8.0.0)
Requires-Dist: redis (>=4.6.0,<5.0.0)
Requires-Dist: tenacity (>=8.2.2,<9.0.0)
Requires-Dist: types-colorama (>=0.4.15.11)
